{
    "톤쇼우": {
        "별점": 4.59,
        "방문자리뷰": 2087,
        "블로그리뷰": 1018
    },
    "수림식당 본점": {
        "방문자리뷰": 1418,
        "블로그리뷰": 562
    },
    "설어정 부산대점": {
        "별점": 4.4,
        "방문자리뷰": 1281,
        "블로그리뷰": 614
    },
    "케어포커피": {
        "방문자리뷰": 22,
        "블로그리뷰": 32
    },
    "하나이미": {
        "별점": 4.63,
        "방문자리뷰": 531,
        "블로그리뷰": 352
    },
    "부산대 포맨티코": {
        "별점": 4.55,
        "방문자리뷰": 1035,
        "블로그리뷰": 708
    },
    "서문국수": {
        "별점": 4.69,
        "방문자리뷰": 343,
        "블로그리뷰": 136
    },
    "쿠카이야": {
        "별점": 4.39,
        "방문자리뷰": 409,
        "블로그리뷰": 279
    },
    "세컨디포레스트 부산대점": {
        "방문자리뷰": 201,
        "블로그리뷰": 107
    },
    "카츠안": {
        "별점": 4.54,
        "방문자리뷰": 837,
        "블로그리뷰": 500
    },
    "자마미등갈비": {
        "별점": 4.65,
        "방문자리뷰": 200,
        "블로그리뷰": 168
    },
    "서빙고본점": {
        "별점": 4.55,
        "방문자리뷰": 234,
        "블로그리뷰": 241
    },
    "만서리 이가네 막국수": {
        "별점": 4.46,
        "방문자리뷰": 1261,
        "블로그리뷰": 317
    },
    "컵넛": {
        "별점": 4.49,
        "방문자리뷰": 577,
        "블로그리뷰": 671
    },
    "시네마파라다이스 X 포도키친": {
        "별점": 4.43,
        "방문자리뷰": 251,
        "블로그리뷰": 350
    },
    "Etalee": {
        "방문자리뷰": 406,
        "블로그리뷰": 502
    },
    "델라고부산대점": {
        "별점": 4.5,
        "방문자리뷰": 417,
        "블로그리뷰": 353
    },
    "수림식당 부산대점": {
        "별점": 4.58,
        "방문자리뷰": 567,
        "블로그리뷰": 244
    },
    "인자한키친": {
        "별점": 4.71,
        "방문자리뷰": 168,
        "블로그리뷰": 199
    },
    "티앤북스": {
        "별점": 4.68,
        "방문자리뷰": 149,
        "블로그리뷰": 166
    },
    "테스투치네": {
        "별점": 4.69,
        "방문자리뷰": 129,
        "블로그리뷰": 165
    },
    "모시모시": {
        "별점": 4.39,
        "방문자리뷰": 348,
        "블로그리뷰": 777
    },
    "에픽키친": {
        "별점": 4.71,
        "방문자리뷰": 303,
        "블로그리뷰": 113
    },
    "4242샌드위치 본점": {
        "별점": 4.69,
        "방문자리뷰": 252,
        "블로그리뷰": 118
    },
    "브로넛": {
        "방문자리뷰": 77,
        "블로그리뷰": 57
    },
    "도르샐러드": {
        "별점": 4.75,
        "방문자리뷰": 543,
        "블로그리뷰": 196
    },
    "구워삶기 부산대점": {
        "별점": 4.48,
        "방문자리뷰": 157,
        "블로그리뷰": 1047
    },
    "카페소록": {
        "별점": 4.54,
        "방문자리뷰": 172,
        "블로그리뷰": 226
    },
    "토비코": {
        "별점": 4.51,
        "방문자리뷰": 464,
        "블로그리뷰": 514
    },
    "백석": {
        "별점": 4.38,
        "방문자리뷰": 80,
        "블로그리뷰": 76
    },
    "이솝페이블": {
        "별점": 4.53,
        "방문자리뷰": 305,
        "블로그리뷰": 379
    },
    "텐동코하루": {
        "별점": 4.4,
        "방문자리뷰": 351,
        "블로그리뷰": 244
    },
    "버거스올마이티 부산대점": {
        "방문자리뷰": 162,
        "블로그리뷰": 71
    },
    "샤오시안": {
        "별점": 4.38,
        "방문자리뷰": 472,
        "블로그리뷰": 674
    },
    "펠로": {
        "방문자리뷰": 213,
        "블로그리뷰": 49
    },
    "부산대우쭈쭈": {
        "별점": 4.55,
        "방문자리뷰": 827,
        "블로그리뷰": 414
    },
    "웬디스키친": {
        "별점": 4.65,
        "방문자리뷰": 216,
        "블로그리뷰": 315
    },
    "의정서": {
        "별점": 4.72,
        "방문자리뷰": 229,
        "블로그리뷰": 258
    },
    "뉴숯불통닭 본점": {
        "별점": 4.64,
        "방문자리뷰": 423,
        "블로그리뷰": 142
    },
    "장수돌곱창": {
        "별점": 4.49,
        "방문자리뷰": 214,
        "블로그리뷰": 182
    }
}